imio.pm.locales-4.2.33-py3.12-nspkg.pth
imio/pm/locales/__init__.py
imio/pm/locales/configure.zcml
imio/pm/locales/locales/PloneMeeting.pot
imio/pm/locales/locales/README.txt
imio/pm/locales/locales/collective.behavior.talcondition.pot
imio/pm/locales/locales/collective.contact.core.pot
imio/pm/locales/locales/collective.documentgenerator.pot
imio/pm/locales/locales/collective.eeafaceted.batchactions.pot
imio/pm/locales/locales/collective.eeafaceted.z3ctable.pot
imio/pm/locales/locales/collective.iconifiedcategory.pot
imio/pm/locales/locales/datagridfield.pot
imio/pm/locales/locales/eea.pot
imio/pm/locales/locales/imio.actionspanel.pot
imio/pm/locales/locales/imio.annex.pot
imio/pm/locales/locales/imio.history.pot
imio/pm/locales/locales/merge_generated.sh
imio/pm/locales/locales/plone.pot
imio/pm/locales/locales/sync_pos.sh
imio/pm/locales/locales/de/LC_MESSAGES/PloneMeeting.po
imio/pm/locales/locales/de/LC_MESSAGES/collective.behavior.talcondition.po
imio/pm/locales/locales/de/LC_MESSAGES/collective.contact.core.po
imio/pm/locales/locales/de/LC_MESSAGES/collective.documentgenerator.po
imio/pm/locales/locales/de/LC_MESSAGES/collective.eeafaceted.batchactions.po
imio/pm/locales/locales/de/LC_MESSAGES/collective.eeafaceted.z3ctable.po
imio/pm/locales/locales/de/LC_MESSAGES/collective.iconifiedcategory.po
imio/pm/locales/locales/de/LC_MESSAGES/datagridfield.po
imio/pm/locales/locales/de/LC_MESSAGES/eea.po
imio/pm/locales/locales/de/LC_MESSAGES/imio.actionspanel.po
imio/pm/locales/locales/de/LC_MESSAGES/imio.annex.po
imio/pm/locales/locales/de/LC_MESSAGES/imio.history.po
imio/pm/locales/locales/de/LC_MESSAGES/plone.po
imio/pm/locales/locales/en/LC_MESSAGES/PloneMeeting.po
imio/pm/locales/locales/en/LC_MESSAGES/collective.behavior.talcondition.po
imio/pm/locales/locales/en/LC_MESSAGES/collective.contact.core.po
imio/pm/locales/locales/en/LC_MESSAGES/collective.documentgenerator.po
imio/pm/locales/locales/en/LC_MESSAGES/collective.eeafaceted.batchactions.po
imio_pm_locales-4.2.33.dist-info/METADATA
imio_pm_locales-4.2.33.dist-info/WHEEL
imio_pm_locales-4.2.33.dist-info/namespace_packages.txt
imio_pm_locales-4.2.33.dist-info/top_level.txt
imio_pm_locales-4.2.33.dist-info/RECORD
