Metadata-Version: 2.4
Name: imio.pm.locales
Version: 4.2.33
Summary: Locales for PloneMeeting
Home-page: https://github.com/IMIO/imio.pm.locales
Author: Gauthier Bastien
Author-email: gauthier@imio.be
License: GPL
Keywords: plone i18n locale translation PloneMeeting egov communesplone imio plonegov
Classifier: Development Status :: 6 - Mature
Classifier: Environment :: Web Environment
Classifier: Framework :: Plone
Classifier: Framework :: Zope2
Classifier: License :: OSI Approved :: GNU General Public License (GPL)
Classifier: Operating System :: OS Independent
Classifier: Programming Language :: Python
Classifier: Programming Language :: Python :: 2.7
Requires-Dist: setuptools
Provides-Extra: test
Requires-Dist: plone.app.testing; extra == "test"
Requires-Dist: unittest2; extra == "test"
Dynamic: author
Dynamic: author-email
Dynamic: classifier
Dynamic: description
Dynamic: home-page
Dynamic: keywords
Dynamic: license
Dynamic: provides-extra
Dynamic: requires-dist
Dynamic: summary
